{
  "title": "27 November",
  "content": [
    {
      "title": "Intro",
      "content": "Add curated event\nNovember\n1\n2\n3\n4\n5\n6\n7\n8\n9\n10\n11\n12\n13\n14\n15\n16\n17\n18\n19\n20\n21\n22\n23\n24\n25\n26\n27\n28\n29\n30\nJan\nFeb\nMar\nApr\nMay\nJun\nJul\nAug\nSep\nOct\nNov\nDec\n\nEvents that occurred on 27 November."
    },
    {
      "title": "On Earth",
      "content": "1899 - Actor Gerik Schjelderup is born.\n1907 - Author L. Sprague de Camp is born.\n1914 - J.R.R. Tolkien reads The Voyage of Eärendel the Evening Star at a poorly attended meeting of Exeter College's Essay Club.\n1914 - J.R.R. Tolkien writes Letter 2.\n1954 - J.R.R. Tolkien writes Letter 157.\n1977 - The 1977 animated version of The Hobbit is broadcast in the United States.\n1993 - Magyar Tolkien Tarsasag, the Hungarian Tolkien Society, is founded.\n1996 - Actress Alexandra Astin is born.\n2001 - Music Inspired by Middle Earth, a musical album featuring many artists, including David Arkenstone, is released.\n2006 - Actor Anthony Jackson dies.\n2012 - The Hobbits: The Many Lives of Bilbo, Frodo, Sam, Merry and Pippin is published."
    },
    {
      "title": "In Arda",
      "content": "T.A. 3018:\nFrodo and Samwise rest in Rivendell and prepare for their quest to destroy the One Ring."
    }
  ]
}